README.txt
setup.py
lib/rootplot/__init__.py
lib/rootplot/core.py
lib/rootplot/root2matplotlib.py
lib/rootplot/rootinfo.py
lib/rootplot/tree2hists.py
lib/rootplot/utilities.py
lib/rootplot/version.py
lib/rootplot.egg-info/PKG-INFO
lib/rootplot.egg-info/SOURCES.txt
lib/rootplot.egg-info/dependency_links.txt
lib/rootplot.egg-info/entry_points.txt
lib/rootplot.egg-info/top_level.txt