Metadata-Version: 1.0
Name: rootplot
Version: 2.2
Summary: Tools for quick and beautiful plotting with ROOT
Home-page: http://packages.python.org/rootplot/
Author: Jeff Klukas
Author-email: klukas@wisc.edu
License: UNKNOWN
Platform: UNKNOWN
Classifier: Development Status :: 5 - Production/Stable
Classifier: Environment :: Console
Classifier: Intended Audience :: Science/Research
Classifier: License :: OSI Approved :: MIT License
Classifier: Natural Language :: English
Classifier: Topic :: Scientific/Engineering :: Visualization
Classifier: Topic :: Utilities
